[{"dataset": "chessweka", "method": "SDD", "drift_detected_mean": 2.0, "drift_detected_std": 0.0, "accuracy_mean": 0.6063241106719368, "accuracy_std": 0.026526421716304403}, {"dataset": "chessweka", "method": "HDD", "drift_detected_mean": 1.0, "drift_detected_std": 0.0, "accuracy_mean": 0.7486166007905138, "accuracy_std": 0.0073309237118543095}, {"dataset": "chessweka", "method": "BDD", "drift_detected_mean": 2.0, "drift_detected_std": 0.0, "accuracy_mean": 0.7122529644268775, "accuracy_std": 0.0029578319263034937}]